rule30py-0.2.0.dist-info/METADATA
rule30py-0.2.0.dist-info/WHEEL
rule30.libs/libgcc_s-b5472b99.so.1
rule30/__init__.py
rule30/rand.py
rule30/py.typed
rule30/rule30py.abi3.so
rule30py-0.2.0.dist-info/RECORD
