Metadata-Version: 2.3
Name: rule30py
Version: 0.2.0
Classifier: Programming Language :: Rust
Classifier: Programming Language :: Python :: Implementation :: CPython
Classifier: Programming Language :: Python :: Implementation :: PyPy
License: Apache-2.0
Requires-Python: >=3.9
Project-URL: documentation, https://github.com/kemingy/rule30
Project-URL: repository, https://github.com/kemingy/rule30
